{
  "nodes": [
    {
      "id": "agent:prodirek",
      "label": "prodirek",
      "type": {
        "category": "agent",
        "type": "agent"
      },
      "x": 178.4637056129421,
      "y": 61.20698017173787,
      "size": 5,
      "color": "#4a90e2"
    },
    {
      "id": "agent:arko",
      "label": "arko",
      "type": {
        "category": "agent",
        "type": "agent"
      },
      "x": 376.0216055823588,
      "y": 7.6834821704986345,
      "size": 5,
      "color": "#4a90e2"
    },
    {
      "id": "view:Home",
      "label": "Home",
      "type": {
        "category": "view",
        "type": "view"
      },
      "x": 190.79996699774063,
      "y": 211.20562907109777,
      "size": 5,
      "color": "#4a90e2"
    },
    {
      "id": "view:Kanban",
      "label": "Kanban",
      "type": {
        "category": "view",
        "type": "view"
      },
      "x": 550.5166224501064,
      "y": 150.48141591779017,
      "size": 5,
      "color": "#4a90e2"
    },
    {
      "id": "view:EisenhowerMatrix",
      "label": "EisenhowerMatrix",
      "type": {
        "category": "view",
        "type": "view"
      },
      "x": 720.7304184384552,
      "y": 190.47745593975293,
      "size": 5,
      "color": "#4a90e2"
    },
    {
      "id": "view:Gantt",
      "label": "Gantt",
      "type": {
        "category": "view",
        "type": "view"
      },
      "x": 688.4963305744274,
      "y": 392.20411058910236,
      "size": 5,
      "color": "#4a90e2"
    },
    {
      "id": "view:Chat",
      "label": "Chat",
      "type": {
        "category": "view",
        "type": "view"
      },
      "x": 465.06870141079685,
      "y": 194.7739597716765,
      "size": 5,
      "color": "#4a90e2"
    },
    {
      "id": "view:DebugGraph",
      "label": "DebugGraph",
      "type": {
        "category": "view",
        "type": "view"
      },
      "x": 469.53556406381836,
      "y": 95.53229705219246,
      "size": 5,
      "color": "#4a90e2"
    },
    {
      "id": "bdd_process:webtests:src_lib_tiposkripto_tests_calculator_calculator-test-web-react-ts-bdd",
      "label": "bdd process for src_lib_tiposkripto_tests_calculator_calculator-test-web-react-ts-bdd",
      "type": {
        "category": "process",
        "type": "bdd"
      },
      "x": 277.31205910690136,
      "y": 455.2549571383492,
      "size": 5,
      "color": "#4a90e2"
    },
    {
      "id": "builder_process:webtests:builder",
      "label": "builder process for builder",
      "type": {
        "category": "process",
        "type": "builder"
      },
      "x": 168.99236788971425,
      "y": 503.749514968788,
      "size": 5,
      "color": "#4a90e2"
    },
    {
      "id": "bdd_process:nodetests:src_lib_tiposkripto_tests_circle_circle-test-ts-bdd",
      "label": "bdd process for src_lib_tiposkripto_tests_circle_circle-test-ts-bdd",
      "type": {
        "category": "process",
        "type": "bdd"
      },
      "x": 324.75910881830856,
      "y": 7.904155003315805,
      "size": 5,
      "color": "#4a90e2"
    },
    {
      "id": "builder_process:nodetests:builder",
      "label": "builder process for builder",
      "type": {
        "category": "process",
        "type": "builder"
      },
      "x": 415.12843329159494,
      "y": 224.90721644993675,
      "size": 5,
      "color": "#4a90e2"
    },
    {
      "id": "bdd_process:webtests:src_lib_tiposkripto_tests_calculator_calculator-test-web-ts-bdd",
      "label": "bdd process for src_lib_tiposkripto_tests_calculator_calculator-test-web-ts-bdd",
      "type": {
        "category": "process",
        "type": "bdd"
      },
      "x": 789.2769929964251,
      "y": 505.2935778690833,
      "size": 5,
      "color": "#4a90e2"
    },
    {
      "id": "bdd_process:nodetests:src_vscode_providers_aiderprocesstreedataprovider-test_aiderprocesstreedataprovider-test-ts-bdd",
      "label": "bdd process for src_vscode_providers_aiderprocesstreedataprovider-test_aiderprocesstreedataprovider-test-ts-bdd",
      "type": {
        "category": "process",
        "type": "bdd"
      },
      "x": 792.3026667125788,
      "y": 541.097626647613,
      "size": 5,
      "color": "#4a90e2"
    },
    {
      "id": "check_process:webtests:src_lib_tiposkripto_tests_calculator_calculator-test-web-react-ts-check-1",
      "label": "check process for src_lib_tiposkripto_tests_calculator_calculator-test-web-react-ts-check-1",
      "type": {
        "category": "process",
        "type": "check"
      },
      "x": 461.8383948063718,
      "y": 336.00993858128686,
      "size": 5,
      "color": "#4a90e2"
    },
    {
      "id": "bdd_process:nodetests:src_lib_tiposkripto_tests_calculator_calculator-test-node-ts-bdd",
      "label": "bdd process for src_lib_tiposkripto_tests_calculator_calculator-test-node-ts-bdd",
      "type": {
        "category": "process",
        "type": "bdd"
      },
      "x": 434.85024239436586,
      "y": 348.03764884314694,
      "size": 5,
      "color": "#4a90e2"
    },
    {
      "id": "check_process:webtests:src_lib_tiposkripto_tests_calculator_calculator-test-web-react-ts-check-0",
      "label": "check process for src_lib_tiposkripto_tests_calculator_calculator-test-web-react-ts-check-0",
      "type": {
        "category": "process",
        "type": "check"
      },
      "x": 225.64692826851393,
      "y": 418.4453707748892,
      "size": 5,
      "color": "#4a90e2"
    },
    {
      "id": "bdd_process:nodetests:src_lib_tiposkripto_tests_abstractbase-test_index-ts-bdd",
      "label": "bdd process for src_lib_tiposkripto_tests_abstractbase-test_index-ts-bdd",
      "type": {
        "category": "process",
        "type": "bdd"
      },
      "x": 704.4277751191123,
      "y": 225.33491896256444,
      "size": 5,
      "color": "#4a90e2"
    },
    {
      "id": "bdd_process:nodetests:src_lib_tiposkripto_tests_rectangle_rectangle-test-ts-bdd",
      "label": "bdd process for src_lib_tiposkripto_tests_rectangle_rectangle-test-ts-bdd",
      "type": {
        "category": "process",
        "type": "bdd"
      },
      "x": 120.28081500812489,
      "y": 154.5512149317222,
      "size": 5,
      "color": "#4a90e2"
    },
    {
      "id": "check_process:webtests:src_lib_tiposkripto_tests_calculator_calculator-test-web-ts-check-1",
      "label": "check process for src_lib_tiposkripto_tests_calculator_calculator-test-web-ts-check-1",
      "type": {
        "category": "process",
        "type": "check"
      },
      "x": 700.8530911333593,
      "y": 162.24150459445687,
      "size": 5,
      "color": "#4a90e2"
    },
    {
      "id": "check_process:webtests:src_lib_tiposkripto_tests_calculator_calculator-test-web-ts-check-0",
      "label": "check process for src_lib_tiposkripto_tests_calculator_calculator-test-web-ts-check-0",
      "type": {
        "category": "process",
        "type": "check"
      },
      "x": 460.19139311120114,
      "y": 268.82785744430527,
      "size": 5,
      "color": "#4a90e2"
    },
    {
      "id": "check_process:webtests:src_lib_tiposkripto_tests_calculator_calculator-test-web-ts-check-1",
      "label": "check process for src_lib_tiposkripto_tests_calculator_calculator-test-web-ts-check-1",
      "type": {
        "category": "process",
        "type": "check"
      },
      "x": 297.80463694938,
      "y": 188.94763937638493,
      "size": 5,
      "color": "#4a90e2"
    },
    {
      "id": "bdd_process:webtests:src_lib_tiposkripto_tests_calculator_calculator-test-web-react-ts-bdd",
      "label": "bdd process for src_lib_tiposkripto_tests_calculator_calculator-test-web-react-ts-bdd",
      "type": {
        "category": "process",
        "type": "bdd"
      },
      "x": 783.3808150236138,
      "y": 77.05804737790262,
      "size": 5,
      "color": "#4a90e2"
    },
    {
      "id": "bdd_process:nodetests:src_lib_tiposkripto_tests_rectangle_rectangle-test-ts-bdd",
      "label": "bdd process for src_lib_tiposkripto_tests_rectangle_rectangle-test-ts-bdd",
      "type": {
        "category": "process",
        "type": "bdd"
      },
      "x": 749.5134016186774,
      "y": 123.25673483636194,
      "size": 5,
      "color": "#4a90e2"
    },
    {
      "id": "builder_process:webtests:builder",
      "label": "builder process for builder",
      "type": {
        "category": "process",
        "type": "builder"
      },
      "x": 129.03626594440442,
      "y": 588.3816989200621,
      "size": 5,
      "color": "#4a90e2"
    },
    {
      "id": "bdd_process:webtests:src_lib_tiposkripto_tests_calculator_calculator-test-web-ts-bdd",
      "label": "bdd process for src_lib_tiposkripto_tests_calculator_calculator-test-web-ts-bdd",
      "type": {
        "category": "process",
        "type": "bdd"
      },
      "x": 101.7487379204602,
      "y": 17.58610599699615,
      "size": 5,
      "color": "#4a90e2"
    },
    {
      "id": "builder_process:nodetests:builder",
      "label": "builder process for builder",
      "type": {
        "category": "process",
        "type": "builder"
      },
      "x": 205.3859084191095,
      "y": 383.21809571052927,
      "size": 5,
      "color": "#4a90e2"
    },
    {
      "id": "bdd_process:nodetests:src_lib_tiposkripto_tests_circle_circle-test-ts-bdd",
      "label": "bdd process for src_lib_tiposkripto_tests_circle_circle-test-ts-bdd",
      "type": {
        "category": "process",
        "type": "bdd"
      },
      "x": 433.3635915357595,
      "y": 137.4300242436841,
      "size": 5,
      "color": "#4a90e2"
    },
    {
      "id": "bdd_process:nodetests:src_vscode_providers_aiderprocesstreedataprovider-test_aiderprocesstreedataprovider-test-ts-bdd",
      "label": "bdd process for src_vscode_providers_aiderprocesstreedataprovider-test_aiderprocesstreedataprovider-test-ts-bdd",
      "type": {
        "category": "process",
        "type": "bdd"
      },
      "x": 47.96863648515721,
      "y": 510.82553895021596,
      "size": 5,
      "color": "#4a90e2"
    },
    {
      "id": "check_process:webtests:src_lib_tiposkripto_tests_calculator_calculator-test-web-react-ts-check-0",
      "label": "check process for src_lib_tiposkripto_tests_calculator_calculator-test-web-react-ts-check-0",
      "type": {
        "category": "process",
        "type": "check"
      },
      "x": 495.6830407694764,
      "y": 61.22687643831455,
      "size": 5,
      "color": "#4a90e2"
    },
    {
      "id": "check_process:webtests:src_lib_tiposkripto_tests_calculator_calculator-test-web-react-ts-check-1",
      "label": "check process for src_lib_tiposkripto_tests_calculator_calculator-test-web-react-ts-check-1",
      "type": {
        "category": "process",
        "type": "check"
      },
      "x": 57.26812453500641,
      "y": 586.7180442765502,
      "size": 5,
      "color": "#4a90e2"
    },
    {
      "id": "bdd_process:nodetests:src_lib_tiposkripto_tests_abstractbase-test_index-ts-bdd",
      "label": "bdd process for src_lib_tiposkripto_tests_abstractbase-test_index-ts-bdd",
      "type": {
        "category": "process",
        "type": "bdd"
      },
      "x": 59.088318837586584,
      "y": 10.970322448636981,
      "size": 5,
      "color": "#4a90e2"
    },
    {
      "id": "check_process:webtests:src_lib_tiposkripto_tests_calculator_calculator-test-web-ts-check-0",
      "label": "check process for src_lib_tiposkripto_tests_calculator_calculator-test-web-ts-check-0",
      "type": {
        "category": "process",
        "type": "check"
      },
      "x": 710.665414958812,
      "y": 382.78720188709644,
      "size": 5,
      "color": "#4a90e2"
    },
    {
      "id": "bdd_process:nodetests:src_lib_tiposkripto_tests_calculator_calculator-test-node-ts-bdd",
      "label": "bdd process for src_lib_tiposkripto_tests_calculator_calculator-test-node-ts-bdd",
      "type": {
        "category": "process",
        "type": "bdd"
      },
      "x": 616.8117497118786,
      "y": 65.98604963304304,
      "size": 5,
      "color": "#4a90e2"
    }
  ],
  "edges": [
    {
      "source": "agent:prodirek",
      "target": "view:Home",
      "type": {
        "category": "association",
        "type": "associatedWith",
        "directed": true
      },
      "attributes": {
        "type": {
          "category": "association",
          "type": "associatedWith",
          "directed": true
        },
        "timestamp": "2026-04-24T22:30:56.147Z"
      }
    },
    {
      "source": "agent:prodirek",
      "target": "view:Kanban",
      "type": {
        "category": "association",
        "type": "associatedWith",
        "directed": true
      },
      "attributes": {
        "type": {
          "category": "association",
          "type": "associatedWith",
          "directed": true
        },
        "timestamp": "2026-04-24T22:30:56.147Z"
      }
    },
    {
      "source": "agent:prodirek",
      "target": "view:EisenhowerMatrix",
      "type": {
        "category": "association",
        "type": "associatedWith",
        "directed": true
      },
      "attributes": {
        "type": {
          "category": "association",
          "type": "associatedWith",
          "directed": true
        },
        "timestamp": "2026-04-24T22:30:56.147Z"
      }
    },
    {
      "source": "agent:prodirek",
      "target": "view:Gantt",
      "type": {
        "category": "association",
        "type": "associatedWith",
        "directed": true
      },
      "attributes": {
        "type": {
          "category": "association",
          "type": "associatedWith",
          "directed": true
        },
        "timestamp": "2026-04-24T22:30:56.147Z"
      }
    },
    {
      "source": "agent:prodirek",
      "target": "view:Chat",
      "type": {
        "category": "association",
        "type": "associatedWith",
        "directed": true
      },
      "attributes": {
        "type": {
          "category": "association",
          "type": "associatedWith",
          "directed": true
        },
        "timestamp": "2026-04-24T22:30:56.147Z"
      }
    },
    {
      "source": "agent:prodirek",
      "target": "view:DebugGraph",
      "type": {
        "category": "association",
        "type": "associatedWith",
        "directed": true
      },
      "attributes": {
        "type": {
          "category": "association",
          "type": "associatedWith",
          "directed": true
        },
        "timestamp": "2026-04-24T22:30:56.147Z"
      }
    },
    {
      "source": "agent:arko",
      "target": "view:Home",
      "type": {
        "category": "association",
        "type": "associatedWith",
        "directed": true
      },
      "attributes": {
        "type": {
          "category": "association",
          "type": "associatedWith",
          "directed": true
        },
        "timestamp": "2026-04-24T22:30:56.147Z"
      }
    },
    {
      "source": "agent:arko",
      "target": "view:Kanban",
      "type": {
        "category": "association",
        "type": "associatedWith",
        "directed": true
      },
      "attributes": {
        "type": {
          "category": "association",
          "type": "associatedWith",
          "directed": true
        },
        "timestamp": "2026-04-24T22:30:56.147Z"
      }
    },
    {
      "source": "agent:arko",
      "target": "view:EisenhowerMatrix",
      "type": {
        "category": "association",
        "type": "associatedWith",
        "directed": true
      },
      "attributes": {
        "type": {
          "category": "association",
          "type": "associatedWith",
          "directed": true
        },
        "timestamp": "2026-04-24T22:30:56.147Z"
      }
    },
    {
      "source": "agent:arko",
      "target": "view:Gantt",
      "type": {
        "category": "association",
        "type": "associatedWith",
        "directed": true
      },
      "attributes": {
        "type": {
          "category": "association",
          "type": "associatedWith",
          "directed": true
        },
        "timestamp": "2026-04-24T22:30:56.147Z"
      }
    },
    {
      "source": "agent:arko",
      "target": "view:Chat",
      "type": {
        "category": "association",
        "type": "associatedWith",
        "directed": true
      },
      "attributes": {
        "type": {
          "category": "association",
          "type": "associatedWith",
          "directed": true
        },
        "timestamp": "2026-04-24T22:30:56.147Z"
      }
    },
    {
      "source": "agent:arko",
      "target": "view:DebugGraph",
      "type": {
        "category": "association",
        "type": "associatedWith",
        "directed": true
      },
      "attributes": {
        "type": {
          "category": "association",
          "type": "associatedWith",
          "directed": true
        },
        "timestamp": "2026-04-24T22:30:56.147Z"
      }
    }
  ],
  "viewType": "debug",
  "timestamp": "2026-04-24T22:31:02.170Z"
}